imageapply/__init__.py
imageapply/data.py
imageapply/flexible_model.py
imageapply/preprocess.py
imageapply/revtransform.py
imageapply/tools.py
imageapply-0.2.2.dist-info/LICENSE
imageapply-0.2.2.dist-info/WHEEL
imageapply-0.2.2.dist-info/METADATA
imageapply-0.2.2.dist-info/RECORD
