Metadata-Version: 2.1
Name: imageapply
Version: 0.2.2
Summary: Simplifies the process of applying U-net style models to large images.
License: LICENSE
Author: fynnsu
Author-email: fynnsu@outlook.com
Requires-Python: >=3.8,<4.0
Classifier: License :: Other/Proprietary License
Classifier: Programming Language :: Python :: 3
Classifier: Programming Language :: Python :: 3.8
Classifier: Programming Language :: Python :: 3.9
Classifier: Programming Language :: Python :: 3.10
Requires-Dist: numpy (>=1,<2)
Requires-Dist: torch (>=1,<2)
